myqqa/__init__.py
myqqa/send.py
myqqa-0.0.1.dist-info/LICENSE
myqqa-0.0.1.dist-info/METADATA
myqqa-0.0.1.dist-info/WHEEL
myqqa-0.0.1.dist-info/top_level.txt
myqqa-0.0.1.dist-info/RECORD
