Metadata-Version: 2.1
Name: myqqa
Version: 0.0.1
Summary: A small example package
Home-page: https://www.kancloud.cn/pythonnic/python/2682628
Author: pythonnic
Author-email: 2696047693@qq.com
License: UNKNOWN
Project-URL: Bug Tracker, https://github.com/maisge/myqq/issues
Platform: UNKNOWN
Classifier: Programming Language :: Python :: 3
Classifier: License :: OSI Approved :: MIT License
Classifier: Operating System :: OS Independent
Requires-Python: >=3.6
License-File: LICENSE
